{
  "extends": "tslint-config-airbnb",
  "rules": {
    "curly": true,
    "trailing-comma": [true],
    "no-string-throw": false,
    "ordered-imports" : false,
    "no-console": [
      true,
      "log",
      "error",
      "debug",
      "info"
    ],
    "no-duplicate-imports": true,
    "no-this-assignment":true,
    "no-parameter-reassignment": true,
    "prefer-template": true,
    "no-debugger": true,
    "no-duplicate-variable": true,
    "no-eval": true,
    "no-invalid-this": true,
    "no-shadowed-variable": true,
    "no-unsafe-finally": true,
    "no-var-keyword": true,
    "triple-equals": [
      true,
      "allow-null-check",
      "allow-undefined-check"
    ],
    "semicolon": [
      true,
      "always",
      "ignore-interfaces"
    ],
    "variable-name": [
      true,
      "ban-keywords",
      "check-format",
      "allow-leading-underscore"
    ],
    "ter-indent": [true, 2]
  }


}
